scrapeit
