Metadata-Version: 1.0
Name: scrapeit
Version: 1.1.0
Summary: Configuration driven web scraping framework
Home-page: https://github.com/JonnyFb421/scrapeit
Author: Jonathon Carlyon
Author-email: JonathonCarlyon@gmail.com
License: UNKNOWN
Platform: UNKNOWN
